porran/__init__.py
porran/create_structure.py
porran/get_zeolite.py
porran/graph_creation.py
porran/mask_method.py
porran/porran.py
porran/replacement_algorithms.py
porran/transformations.py
porran/utils.py
porran-0.0.11.dist-info/licenses/LICENSE
porran-0.0.11.dist-info/METADATA
porran-0.0.11.dist-info/WHEEL
porran-0.0.11.dist-info/top_level.txt
porran-0.0.11.dist-info/RECORD
