Metadata-Version: 2.4
Name: porran
Version: 0.0.11
Summary: PORous RANdom crystal structure generation
Author-email: Marko Petkovic <m.petkovic1@tue.nl>, Koen Wortelboer <k.a.wortelboer1@tue.nl>
Project-URL: home-page, https://github.com/marko-petkovic/porran
Classifier: Programming Language :: Python :: 3
Classifier: License :: OSI Approved :: MIT License
Classifier: Operating System :: OS Independent
Requires-Python: >=3.8
License-File: LICENSE
Requires-Dist: numpy
Requires-Dist: pymatgen
Requires-Dist: networkx
Requires-Dist: requests
Dynamic: license-file
